viegenere_message_encoder_GameDevNoOne/Ascii_Art_coll.txt
viegenere_message_encoder_GameDevNoOne/General_Purpos_Lib.py
viegenere_message_encoder_GameDevNoOne/Test_VTG.py
viegenere_message_encoder_GameDevNoOne/Vigenere_Table_Generator.py
viegenere_message_encoder_GameDevNoOne/__init__.py
viegenere_message_encoder_gamedevnoone-1.0.0.dist-info/METADATA
viegenere_message_encoder_gamedevnoone-1.0.0.dist-info/WHEEL
viegenere_message_encoder_gamedevnoone-1.0.0.dist-info/licenses/LICENSE
viegenere_message_encoder_gamedevnoone-1.0.0.dist-info/RECORD
