Metadata-Version: 2.3
Name: viegenere_message_encoder_GameDevNoOne
Version: 1.0.0
Summary: An encoder of messages
Project-URL: Homepage, https://github.com/GameDevNoOne/Vigener_Coder_n_Decoder
Project-URL: Issues, https://github.com/GameDevNoOne/Vigener_Coder_n_Decoder/issues
Author-email: NoOne <noonegamedev1@gmail.com>
Classifier: License :: OSI Approved :: MIT License
Classifier: Operating System :: OS Independent
Classifier: Programming Language :: Python :: 3
Requires-Python: >=3.8
